bittest/__init__.py
bittest/__init__old.py
bittest-0.0.3.dist-info/LICENSE.txt
bittest-0.0.3.dist-info/METADATA
bittest-0.0.3.dist-info/WHEEL
bittest-0.0.3.dist-info/top_level.txt
bittest-0.0.3.dist-info/RECORD
